{
	"textures": [
		{
			"image": "rpg_ui.png",
			"format": "RGBA8888",
			"size": {
				"w": 1376,
				"h": 128
			},
			"scale": 1,
			"frames": [
				{
					"filename": "splitted/borders/single/RPG_GUI_v1_selection-0043",
					"rotated": false,
					"trimmed": false,
					"sourceSize": {
						"w": 285,
						"h": 56
					},
					"spriteSourceSize": {
						"x": 0,
						"y": 0,
						"w": 285,
						"h": 56
					},
					"frame": {
						"x": 1,
						"y": 1,
						"w": 285,
						"h": 56
					}
				},
				{
					"filename": "splitted/borders/single/RPG_GUI_v1_selection-0060",
					"rotated": false,
					"trimmed": false,
					"sourceSize": {
						"w": 285,
						"h": 56
					},
					"spriteSourceSize": {
						"x": 0,
						"y": 0,
						"w": 285,
						"h": 56
					},
					"frame": {
						"x": 1,
						"y": 59,
						"w": 285,
						"h": 56
					}
				},
				{
					"filename": "splitted/dividers/RPG_GUI_v1_selection-0070",
					"rotated": false,
					"trimmed": false,
					"sourceSize": {
						"w": 285,
						"h": 56
					},
					"spriteSourceSize": {
						"x": 0,
						"y": 0,
						"w": 285,
						"h": 56
					},
					"frame": {
						"x": 288,
						"y": 1,
						"w": 285,
						"h": 56
					}
				},
				{
					"filename": "splitted/dividers/RPG_GUI_v1_selection-0079",
					"rotated": false,
					"trimmed": false,
					"sourceSize": {
						"w": 285,
						"h": 56
					},
					"spriteSourceSize": {
						"x": 0,
						"y": 0,
						"w": 285,
						"h": 56
					},
					"frame": {
						"x": 288,
						"y": 59,
						"w": 285,
						"h": 56
					}
				},
				{
					"filename": "splitted/borders/single/RPG_GUI_v1_selection-0100",
					"rotated": false,
					"trimmed": false,
					"sourceSize": {
						"w": 129,
						"h": 10
					},
					"spriteSourceSize": {
						"x": 0,
						"y": 0,
						"w": 129,
						"h": 10
					},
					"frame": {
						"x": 1,
						"y": 117,
						"w": 129,
						"h": 10
					}
				},
				{
					"filename": "splitted/borders/single/RPG_GUI_v1_selection-0102",
					"rotated": false,
					"trimmed": false,
					"sourceSize": {
						"w": 129,
						"h": 10
					},
					"spriteSourceSize": {
						"x": 0,
						"y": 0,
						"w": 129,
						"h": 10
					},
					"frame": {
						"x": 132,
						"y": 117,
						"w": 129,
						"h": 10
					}
				},
				{
					"filename": "splitted/borders/single/RPG_GUI_v1_selection-0104",
					"rotated": false,
					"trimmed": false,
					"sourceSize": {
						"w": 129,
						"h": 10
					},
					"spriteSourceSize": {
						"x": 0,
						"y": 0,
						"w": 129,
						"h": 10
					},
					"frame": {
						"x": 263,
						"y": 117,
						"w": 129,
						"h": 10
					}
				},
				{
					"filename": "splitted/borders/single/RPG_GUI_v1_selection-0106",
					"rotated": false,
					"trimmed": false,
					"sourceSize": {
						"w": 129,
						"h": 10
					},
					"spriteSourceSize": {
						"x": 0,
						"y": 0,
						"w": 129,
						"h": 10
					},
					"frame": {
						"x": 394,
						"y": 117,
						"w": 129,
						"h": 10
					}
				},
				{
					"filename": "splitted/borders/single/RPG_GUI_v1_selection-0033",
					"rotated": false,
					"trimmed": false,
					"sourceSize": {
						"w": 208,
						"h": 18
					},
					"spriteSourceSize": {
						"x": 0,
						"y": 0,
						"w": 208,
						"h": 18
					},
					"frame": {
						"x": 575,
						"y": 1,
						"w": 208,
						"h": 18
					}
				},
				{
					"filename": "splitted/borders/single/RPG_GUI_v1_selection-0034",
					"rotated": false,
					"trimmed": false,
					"sourceSize": {
						"w": 205,
						"h": 13
					},
					"spriteSourceSize": {
						"x": 0,
						"y": 0,
						"w": 205,
						"h": 13
					},
					"frame": {
						"x": 575,
						"y": 21,
						"w": 205,
						"h": 13
					}
				},
				{
					"filename": "splitted/borders/RPG_GUI_v1_selection-0092",
					"rotated": false,
					"trimmed": false,
					"sourceSize": {
						"w": 84,
						"h": 83
					},
					"spriteSourceSize": {
						"x": 0,
						"y": 0,
						"w": 84,
						"h": 83
					},
					"frame": {
						"x": 575,
						"y": 36,
						"w": 84,
						"h": 83
					}
				},
				{
					"filename": "splitted/borders/RPG_GUI_v1_selection-0095",
					"rotated": false,
					"trimmed": false,
					"sourceSize": {
						"w": 46,
						"h": 46
					},
					"spriteSourceSize": {
						"x": 0,
						"y": 0,
						"w": 46,
						"h": 46
					},
					"frame": {
						"x": 661,
						"y": 36,
						"w": 46,
						"h": 46
					}
				},
				{
					"filename": "splitted/borders/double/RPG_GUI_v1_selection-0058",
					"rotated": false,
					"trimmed": false,
					"sourceSize": {
						"w": 73,
						"h": 15
					},
					"spriteSourceSize": {
						"x": 0,
						"y": 0,
						"w": 73,
						"h": 15
					},
					"frame": {
						"x": 785,
						"y": 1,
						"w": 73,
						"h": 15
					}
				},
				{
					"filename": "splitted/borders/double/RPG_GUI_v1_selection-0074",
					"rotated": false,
					"trimmed": false,
					"sourceSize": {
						"w": 73,
						"h": 15
					},
					"spriteSourceSize": {
						"x": 0,
						"y": 0,
						"w": 73,
						"h": 15
					},
					"frame": {
						"x": 860,
						"y": 1,
						"w": 73,
						"h": 15
					}
				},
				{
					"filename": "splitted/borders/RPG_GUI_v1_selection-0014",
					"rotated": false,
					"trimmed": false,
					"sourceSize": {
						"w": 24,
						"h": 43
					},
					"spriteSourceSize": {
						"x": 0,
						"y": 0,
						"w": 24,
						"h": 43
					},
					"frame": {
						"x": 661,
						"y": 84,
						"w": 24,
						"h": 43
					}
				},
				{
					"filename": "splitted/borders/single/RPG_GUI_v1_selection-0086",
					"rotated": false,
					"trimmed": false,
					"sourceSize": {
						"w": 74,
						"h": 10
					},
					"spriteSourceSize": {
						"x": 0,
						"y": 0,
						"w": 74,
						"h": 10
					},
					"frame": {
						"x": 935,
						"y": 1,
						"w": 74,
						"h": 10
					}
				},
				{
					"filename": "splitted/borders/single/RPG_GUI_v1_selection-0098",
					"rotated": false,
					"trimmed": false,
					"sourceSize": {
						"w": 74,
						"h": 10
					},
					"spriteSourceSize": {
						"x": 0,
						"y": 0,
						"w": 74,
						"h": 10
					},
					"frame": {
						"x": 1011,
						"y": 1,
						"w": 74,
						"h": 10
					}
				},
				{
					"filename": "splitted/buttons/RPG_GUI_v1_selection-0066",
					"rotated": false,
					"trimmed": false,
					"sourceSize": {
						"w": 37,
						"h": 39
					},
					"spriteSourceSize": {
						"x": 0,
						"y": 0,
						"w": 37,
						"h": 39
					},
					"frame": {
						"x": 709,
						"y": 36,
						"w": 37,
						"h": 39
					}
				},
				{
					"filename": "splitted/buttons/RPG_GUI_v1_selection-0065",
					"rotated": false,
					"trimmed": false,
					"sourceSize": {
						"w": 37,
						"h": 38
					},
					"spriteSourceSize": {
						"x": 0,
						"y": 0,
						"w": 37,
						"h": 38
					},
					"frame": {
						"x": 748,
						"y": 36,
						"w": 37,
						"h": 38
					}
				},
				{
					"filename": "splitted/borders/RPG_GUI_v1_selection-0099",
					"rotated": false,
					"trimmed": false,
					"sourceSize": {
						"w": 19,
						"h": 40
					},
					"spriteSourceSize": {
						"x": 0,
						"y": 0,
						"w": 19,
						"h": 40
					},
					"frame": {
						"x": 687,
						"y": 84,
						"w": 19,
						"h": 40
					}
				},
				{
					"filename": "splitted/buttons/RPG_GUI_v1_selection-0067",
					"rotated": false,
					"trimmed": false,
					"sourceSize": {
						"w": 39,
						"h": 37
					},
					"spriteSourceSize": {
						"x": 0,
						"y": 0,
						"w": 39,
						"h": 37
					},
					"frame": {
						"x": 787,
						"y": 18,
						"w": 39,
						"h": 37
					}
				},
				{
					"filename": "splitted/buttons/RPG_GUI_v1_selection-0068",
					"rotated": false,
					"trimmed": false,
					"sourceSize": {
						"w": 39,
						"h": 37
					},
					"spriteSourceSize": {
						"x": 0,
						"y": 0,
						"w": 39,
						"h": 37
					},
					"frame": {
						"x": 828,
						"y": 18,
						"w": 39,
						"h": 37
					}
				},
				{
					"filename": "splitted/borders/RPG_GUI_v1_selection-0018",
					"rotated": false,
					"trimmed": false,
					"sourceSize": {
						"w": 43,
						"h": 23
					},
					"spriteSourceSize": {
						"x": 0,
						"y": 0,
						"w": 43,
						"h": 23
					},
					"frame": {
						"x": 869,
						"y": 18,
						"w": 43,
						"h": 23
					}
				},
				{
					"filename": "splitted/borders/double/RPG_GUI_v1_selection-0048",
					"rotated": false,
					"trimmed": false,
					"sourceSize": {
						"w": 31,
						"h": 23
					},
					"spriteSourceSize": {
						"x": 0,
						"y": 0,
						"w": 31,
						"h": 23
					},
					"frame": {
						"x": 787,
						"y": 57,
						"w": 31,
						"h": 23
					}
				},
				{
					"filename": "splitted/borders/double/RPG_GUI_v1_selection-0064",
					"rotated": false,
					"trimmed": false,
					"sourceSize": {
						"w": 31,
						"h": 31
					},
					"spriteSourceSize": {
						"x": 0,
						"y": 0,
						"w": 31,
						"h": 31
					},
					"frame": {
						"x": 820,
						"y": 57,
						"w": 31,
						"h": 31
					}
				},
				{
					"filename": "splitted/borders/RPG_GUI_v1_selection-0101",
					"rotated": false,
					"trimmed": false,
					"sourceSize": {
						"w": 19,
						"h": 40
					},
					"spriteSourceSize": {
						"x": 0,
						"y": 0,
						"w": 19,
						"h": 40
					},
					"frame": {
						"x": 853,
						"y": 57,
						"w": 19,
						"h": 40
					}
				},
				{
					"filename": "splitted/borders/single/RPG_GUI_v1_selection-0062",
					"rotated": false,
					"trimmed": false,
					"sourceSize": {
						"w": 15,
						"h": 55
					},
					"spriteSourceSize": {
						"x": 0,
						"y": 0,
						"w": 15,
						"h": 55
					},
					"frame": {
						"x": 874,
						"y": 43,
						"w": 15,
						"h": 55
					}
				},
				{
					"filename": "splitted/borders/single/RPG_GUI_v1_selection-0063",
					"rotated": false,
					"trimmed": false,
					"sourceSize": {
						"w": 15,
						"h": 55
					},
					"spriteSourceSize": {
						"x": 0,
						"y": 0,
						"w": 15,
						"h": 55
					},
					"frame": {
						"x": 891,
						"y": 43,
						"w": 15,
						"h": 55
					}
				},
				{
					"filename": "splitted/borders/single/RPG_GUI_v1_selection-0089",
					"rotated": false,
					"trimmed": false,
					"sourceSize": {
						"w": 10,
						"h": 59
					},
					"spriteSourceSize": {
						"x": 0,
						"y": 0,
						"w": 10,
						"h": 59
					},
					"frame": {
						"x": 908,
						"y": 43,
						"w": 10,
						"h": 59
					}
				},
				{
					"filename": "splitted/borders/double/RPG_GUI_v1_selection-0069",
					"rotated": false,
					"trimmed": false,
					"sourceSize": {
						"w": 31,
						"h": 23
					},
					"spriteSourceSize": {
						"x": 0,
						"y": 0,
						"w": 31,
						"h": 23
					},
					"frame": {
						"x": 708,
						"y": 104,
						"w": 31,
						"h": 23
					}
				},
				{
					"filename": "splitted/checkboxes/RPG_GUI_v1_selection-0005",
					"rotated": false,
					"trimmed": false,
					"sourceSize": {
						"w": 26,
						"h": 25
					},
					"spriteSourceSize": {
						"x": 0,
						"y": 0,
						"w": 26,
						"h": 25
					},
					"frame": {
						"x": 709,
						"y": 77,
						"w": 26,
						"h": 25
					}
				},
				{
					"filename": "splitted/borders/single/RPG_GUI_v1_selection-0090",
					"rotated": false,
					"trimmed": false,
					"sourceSize": {
						"w": 10,
						"h": 59
					},
					"spriteSourceSize": {
						"x": 0,
						"y": 0,
						"w": 10,
						"h": 59
					},
					"frame": {
						"x": 920,
						"y": 18,
						"w": 10,
						"h": 59
					}
				},
				{
					"filename": "splitted/buttons/RPG_GUI_v1_selection-0010",
					"rotated": false,
					"trimmed": false,
					"sourceSize": {
						"w": 31,
						"h": 29
					},
					"spriteSourceSize": {
						"x": 0,
						"y": 0,
						"w": 31,
						"h": 29
					},
					"frame": {
						"x": 1087,
						"y": 1,
						"w": 31,
						"h": 29
					}
				},
				{
					"filename": "splitted/buttons/RPG_GUI_v1_selection-0013",
					"rotated": false,
					"trimmed": false,
					"sourceSize": {
						"w": 31,
						"h": 29
					},
					"spriteSourceSize": {
						"x": 0,
						"y": 0,
						"w": 31,
						"h": 29
					},
					"frame": {
						"x": 1120,
						"y": 1,
						"w": 31,
						"h": 29
					}
				},
				{
					"filename": "splitted/buttons/RPG_GUI_v1_selection-0015",
					"rotated": false,
					"trimmed": false,
					"sourceSize": {
						"w": 31,
						"h": 29
					},
					"spriteSourceSize": {
						"x": 0,
						"y": 0,
						"w": 31,
						"h": 29
					},
					"frame": {
						"x": 1153,
						"y": 1,
						"w": 31,
						"h": 29
					}
				},
				{
					"filename": "splitted/buttons/RPG_GUI_v1_selection-0016",
					"rotated": false,
					"trimmed": false,
					"sourceSize": {
						"w": 31,
						"h": 29
					},
					"spriteSourceSize": {
						"x": 0,
						"y": 0,
						"w": 31,
						"h": 29
					},
					"frame": {
						"x": 1186,
						"y": 1,
						"w": 31,
						"h": 29
					}
				},
				{
					"filename": "splitted/buttons/RPG_GUI_v1_selection-0027",
					"rotated": false,
					"trimmed": false,
					"sourceSize": {
						"w": 31,
						"h": 29
					},
					"spriteSourceSize": {
						"x": 0,
						"y": 0,
						"w": 31,
						"h": 29
					},
					"frame": {
						"x": 1219,
						"y": 1,
						"w": 31,
						"h": 29
					}
				},
				{
					"filename": "splitted/buttons/RPG_GUI_v1_selection-0030",
					"rotated": false,
					"trimmed": false,
					"sourceSize": {
						"w": 31,
						"h": 29
					},
					"spriteSourceSize": {
						"x": 0,
						"y": 0,
						"w": 31,
						"h": 29
					},
					"frame": {
						"x": 1252,
						"y": 1,
						"w": 31,
						"h": 29
					}
				},
				{
					"filename": "splitted/buttons/RPG_GUI_v1_selection-0031",
					"rotated": false,
					"trimmed": false,
					"sourceSize": {
						"w": 31,
						"h": 29
					},
					"spriteSourceSize": {
						"x": 0,
						"y": 0,
						"w": 31,
						"h": 29
					},
					"frame": {
						"x": 1285,
						"y": 1,
						"w": 31,
						"h": 29
					}
				},
				{
					"filename": "splitted/buttons/RPG_GUI_v1_selection-0032",
					"rotated": false,
					"trimmed": false,
					"sourceSize": {
						"w": 31,
						"h": 29
					},
					"spriteSourceSize": {
						"x": 0,
						"y": 0,
						"w": 31,
						"h": 29
					},
					"frame": {
						"x": 1318,
						"y": 1,
						"w": 31,
						"h": 29
					}
				},
				{
					"filename": "splitted/borders/double/RPG_GUI_v1_selection-0057",
					"rotated": false,
					"trimmed": false,
					"sourceSize": {
						"w": 24,
						"h": 24
					},
					"spriteSourceSize": {
						"x": 0,
						"y": 0,
						"w": 24,
						"h": 24
					},
					"frame": {
						"x": 1351,
						"y": 1,
						"w": 24,
						"h": 24
					}
				},
				{
					"filename": "splitted/borders/double/RPG_GUI_v1_selection-0059",
					"rotated": false,
					"trimmed": false,
					"sourceSize": {
						"w": 24,
						"h": 24
					},
					"spriteSourceSize": {
						"x": 0,
						"y": 0,
						"w": 24,
						"h": 24
					},
					"frame": {
						"x": 1351,
						"y": 27,
						"w": 24,
						"h": 24
					}
				},
				{
					"filename": "splitted/borders/single/RPG_GUI_v1_selection-0082",
					"rotated": false,
					"trimmed": false,
					"sourceSize": {
						"w": 13,
						"h": 10
					},
					"spriteSourceSize": {
						"x": 0,
						"y": 0,
						"w": 13,
						"h": 10
					},
					"frame": {
						"x": 525,
						"y": 117,
						"w": 13,
						"h": 10
					}
				},
				{
					"filename": "splitted/borders/single/RPG_GUI_v1_selection-0083",
					"rotated": false,
					"trimmed": false,
					"sourceSize": {
						"w": 13,
						"h": 10
					},
					"spriteSourceSize": {
						"x": 0,
						"y": 0,
						"w": 13,
						"h": 10
					},
					"frame": {
						"x": 540,
						"y": 117,
						"w": 13,
						"h": 10
					}
				},
				{
					"filename": "splitted/checkboxes/RPG_GUI_v1_selection-0006",
					"rotated": false,
					"trimmed": false,
					"sourceSize": {
						"w": 26,
						"h": 25
					},
					"spriteSourceSize": {
						"x": 0,
						"y": 0,
						"w": 26,
						"h": 25
					},
					"frame": {
						"x": 737,
						"y": 77,
						"w": 26,
						"h": 25
					}
				},
				{
					"filename": "splitted/borders/RPG_GUI_v1_selection-0017",
					"rotated": false,
					"trimmed": false,
					"sourceSize": {
						"w": 20,
						"h": 30
					},
					"spriteSourceSize": {
						"x": 0,
						"y": 0,
						"w": 20,
						"h": 30
					},
					"frame": {
						"x": 765,
						"y": 76,
						"w": 20,
						"h": 30
					}
				},
				{
					"filename": "splitted/buttons/RPG_GUI_v1_selection-0037",
					"rotated": false,
					"trimmed": false,
					"sourceSize": {
						"w": 31,
						"h": 29
					},
					"spriteSourceSize": {
						"x": 0,
						"y": 0,
						"w": 31,
						"h": 29
					},
					"frame": {
						"x": 787,
						"y": 82,
						"w": 31,
						"h": 29
					}
				},
				{
					"filename": "splitted/buttons/RPG_GUI_v1_selection-0040",
					"rotated": false,
					"trimmed": false,
					"sourceSize": {
						"w": 31,
						"h": 29
					},
					"spriteSourceSize": {
						"x": 0,
						"y": 0,
						"w": 31,
						"h": 29
					},
					"frame": {
						"x": 820,
						"y": 90,
						"w": 31,
						"h": 29
					}
				},
				{
					"filename": "splitted/borders/single/RPG_GUI_v1_selection-0085",
					"rotated": false,
					"trimmed": false,
					"sourceSize": {
						"w": 19,
						"h": 19
					},
					"spriteSourceSize": {
						"x": 0,
						"y": 0,
						"w": 19,
						"h": 19
					},
					"frame": {
						"x": 853,
						"y": 99,
						"w": 19,
						"h": 19
					}
				},
				{
					"filename": "splitted/checkboxes/RPG_GUI_v1_selection-0022",
					"rotated": false,
					"trimmed": false,
					"sourceSize": {
						"w": 29,
						"h": 26
					},
					"spriteSourceSize": {
						"x": 0,
						"y": 0,
						"w": 29,
						"h": 26
					},
					"frame": {
						"x": 874,
						"y": 100,
						"w": 29,
						"h": 26
					}
				},
				{
					"filename": "splitted/borders/single/RPG_GUI_v1_selection-0087",
					"rotated": false,
					"trimmed": false,
					"sourceSize": {
						"w": 19,
						"h": 19
					},
					"spriteSourceSize": {
						"x": 0,
						"y": 0,
						"w": 19,
						"h": 19
					},
					"frame": {
						"x": 741,
						"y": 104,
						"w": 19,
						"h": 19
					}
				},
				{
					"filename": "splitted/borders/single/RPG_GUI_v1_selection-0096",
					"rotated": false,
					"trimmed": false,
					"sourceSize": {
						"w": 19,
						"h": 19
					},
					"spriteSourceSize": {
						"x": 0,
						"y": 0,
						"w": 19,
						"h": 19
					},
					"frame": {
						"x": 762,
						"y": 108,
						"w": 19,
						"h": 19
					}
				},
				{
					"filename": "splitted/borders/double/RPG_GUI_v1_selection-0046",
					"rotated": false,
					"trimmed": false,
					"sourceSize": {
						"w": 15,
						"h": 14
					},
					"spriteSourceSize": {
						"x": 0,
						"y": 0,
						"w": 15,
						"h": 14
					},
					"frame": {
						"x": 783,
						"y": 113,
						"w": 15,
						"h": 14
					}
				},
				{
					"filename": "splitted/borders/double/RPG_GUI_v1_selection-0047",
					"rotated": false,
					"trimmed": false,
					"sourceSize": {
						"w": 15,
						"h": 14
					},
					"spriteSourceSize": {
						"x": 0,
						"y": 0,
						"w": 15,
						"h": 14
					},
					"frame": {
						"x": 800,
						"y": 113,
						"w": 15,
						"h": 14
					}
				},
				{
					"filename": "splitted/buttons/RPG_GUI_v1_selection-0041",
					"rotated": false,
					"trimmed": false,
					"sourceSize": {
						"w": 31,
						"h": 29
					},
					"spriteSourceSize": {
						"x": 0,
						"y": 0,
						"w": 31,
						"h": 29
					},
					"frame": {
						"x": 935,
						"y": 13,
						"w": 31,
						"h": 29
					}
				},
				{
					"filename": "splitted/buttons/RPG_GUI_v1_selection-0042",
					"rotated": false,
					"trimmed": false,
					"sourceSize": {
						"w": 31,
						"h": 29
					},
					"spriteSourceSize": {
						"x": 0,
						"y": 0,
						"w": 31,
						"h": 29
					},
					"frame": {
						"x": 968,
						"y": 13,
						"w": 31,
						"h": 29
					}
				},
				{
					"filename": "splitted/buttons/RPG_GUI_v1_selection-0051",
					"rotated": false,
					"trimmed": false,
					"sourceSize": {
						"w": 31,
						"h": 29
					},
					"spriteSourceSize": {
						"x": 0,
						"y": 0,
						"w": 31,
						"h": 29
					},
					"frame": {
						"x": 1001,
						"y": 13,
						"w": 31,
						"h": 29
					}
				},
				{
					"filename": "splitted/buttons/RPG_GUI_v1_selection-0054",
					"rotated": false,
					"trimmed": false,
					"sourceSize": {
						"w": 31,
						"h": 29
					},
					"spriteSourceSize": {
						"x": 0,
						"y": 0,
						"w": 31,
						"h": 29
					},
					"frame": {
						"x": 1034,
						"y": 13,
						"w": 31,
						"h": 29
					}
				},
				{
					"filename": "splitted/borders/single/RPG_GUI_v1_selection-0088",
					"rotated": false,
					"trimmed": false,
					"sourceSize": {
						"w": 18,
						"h": 26
					},
					"spriteSourceSize": {
						"x": 0,
						"y": 0,
						"w": 18,
						"h": 26
					},
					"frame": {
						"x": 1067,
						"y": 13,
						"w": 18,
						"h": 26
					}
				},
				{
					"filename": "splitted/buttons/RPG_GUI_v1_selection-0009",
					"rotated": false,
					"trimmed": false,
					"sourceSize": {
						"w": 30,
						"h": 30
					},
					"spriteSourceSize": {
						"x": 0,
						"y": 0,
						"w": 30,
						"h": 30
					},
					"frame": {
						"x": 932,
						"y": 44,
						"w": 30,
						"h": 30
					}
				},
				{
					"filename": "splitted/buttons/RPG_GUI_v1_selection-0012",
					"rotated": false,
					"trimmed": false,
					"sourceSize": {
						"w": 30,
						"h": 30
					},
					"spriteSourceSize": {
						"x": 0,
						"y": 0,
						"w": 30,
						"h": 30
					},
					"frame": {
						"x": 964,
						"y": 44,
						"w": 30,
						"h": 30
					}
				},
				{
					"filename": "splitted/buttons/RPG_GUI_v1_selection-0026",
					"rotated": false,
					"trimmed": false,
					"sourceSize": {
						"w": 30,
						"h": 30
					},
					"spriteSourceSize": {
						"x": 0,
						"y": 0,
						"w": 30,
						"h": 30
					},
					"frame": {
						"x": 996,
						"y": 44,
						"w": 30,
						"h": 30
					}
				},
				{
					"filename": "splitted/buttons/RPG_GUI_v1_selection-0029",
					"rotated": false,
					"trimmed": false,
					"sourceSize": {
						"w": 30,
						"h": 30
					},
					"spriteSourceSize": {
						"x": 0,
						"y": 0,
						"w": 30,
						"h": 30
					},
					"frame": {
						"x": 1028,
						"y": 44,
						"w": 30,
						"h": 30
					}
				},
				{
					"filename": "splitted/buttons/RPG_GUI_v1_selection-0055",
					"rotated": false,
					"trimmed": false,
					"sourceSize": {
						"w": 31,
						"h": 29
					},
					"spriteSourceSize": {
						"x": 0,
						"y": 0,
						"w": 31,
						"h": 29
					},
					"frame": {
						"x": 1087,
						"y": 32,
						"w": 31,
						"h": 29
					}
				},
				{
					"filename": "splitted/buttons/RPG_GUI_v1_selection-0056",
					"rotated": false,
					"trimmed": false,
					"sourceSize": {
						"w": 31,
						"h": 29
					},
					"spriteSourceSize": {
						"x": 0,
						"y": 0,
						"w": 31,
						"h": 29
					},
					"frame": {
						"x": 1120,
						"y": 32,
						"w": 31,
						"h": 29
					}
				},
				{
					"filename": "splitted/buttons/RPG_GUI_v1_selection-0076",
					"rotated": false,
					"trimmed": false,
					"sourceSize": {
						"w": 31,
						"h": 29
					},
					"spriteSourceSize": {
						"x": 0,
						"y": 0,
						"w": 31,
						"h": 29
					},
					"frame": {
						"x": 1153,
						"y": 32,
						"w": 31,
						"h": 29
					}
				},
				{
					"filename": "splitted/buttons/RPG_GUI_v1_selection-0078",
					"rotated": false,
					"trimmed": false,
					"sourceSize": {
						"w": 31,
						"h": 29
					},
					"spriteSourceSize": {
						"x": 0,
						"y": 0,
						"w": 31,
						"h": 29
					},
					"frame": {
						"x": 1186,
						"y": 32,
						"w": 31,
						"h": 29
					}
				},
				{
					"filename": "splitted/buttons/RPG_GUI_v1_selection-0036",
					"rotated": false,
					"trimmed": false,
					"sourceSize": {
						"w": 30,
						"h": 30
					},
					"spriteSourceSize": {
						"x": 0,
						"y": 0,
						"w": 30,
						"h": 30
					},
					"frame": {
						"x": 1219,
						"y": 32,
						"w": 30,
						"h": 30
					}
				},
				{
					"filename": "splitted/buttons/RPG_GUI_v1_selection-0039",
					"rotated": false,
					"trimmed": false,
					"sourceSize": {
						"w": 30,
						"h": 30
					},
					"spriteSourceSize": {
						"x": 0,
						"y": 0,
						"w": 30,
						"h": 30
					},
					"frame": {
						"x": 1251,
						"y": 32,
						"w": 30,
						"h": 30
					}
				},
				{
					"filename": "splitted/buttons/RPG_GUI_v1_selection-0050",
					"rotated": false,
					"trimmed": false,
					"sourceSize": {
						"w": 30,
						"h": 30
					},
					"spriteSourceSize": {
						"x": 0,
						"y": 0,
						"w": 30,
						"h": 30
					},
					"frame": {
						"x": 1283,
						"y": 32,
						"w": 30,
						"h": 30
					}
				},
				{
					"filename": "splitted/buttons/RPG_GUI_v1_selection-0053",
					"rotated": false,
					"trimmed": false,
					"sourceSize": {
						"w": 30,
						"h": 30
					},
					"spriteSourceSize": {
						"x": 0,
						"y": 0,
						"w": 30,
						"h": 30
					},
					"frame": {
						"x": 1315,
						"y": 32,
						"w": 30,
						"h": 30
					}
				},
				{
					"filename": "splitted/borders/single/RPG_GUI_v1_selection-0094",
					"rotated": false,
					"trimmed": false,
					"sourceSize": {
						"w": 18,
						"h": 26
					},
					"spriteSourceSize": {
						"x": 0,
						"y": 0,
						"w": 18,
						"h": 26
					},
					"frame": {
						"x": 1067,
						"y": 41,
						"w": 18,
						"h": 26
					}
				},
				{
					"filename": "splitted/buttons/RPG_GUI_v1_selection-0075",
					"rotated": false,
					"trimmed": false,
					"sourceSize": {
						"w": 30,
						"h": 30
					},
					"spriteSourceSize": {
						"x": 0,
						"y": 0,
						"w": 30,
						"h": 30
					},
					"frame": {
						"x": 1087,
						"y": 63,
						"w": 30,
						"h": 30
					}
				},
				{
					"filename": "splitted/buttons/RPG_GUI_v1_selection-0011",
					"rotated": false,
					"trimmed": false,
					"sourceSize": {
						"w": 29,
						"h": 30
					},
					"spriteSourceSize": {
						"x": 0,
						"y": 0,
						"w": 29,
						"h": 30
					},
					"frame": {
						"x": 1119,
						"y": 63,
						"w": 29,
						"h": 30
					}
				},
				{
					"filename": "splitted/buttons/RPG_GUI_v1_selection-0025",
					"rotated": false,
					"trimmed": false,
					"sourceSize": {
						"w": 29,
						"h": 30
					},
					"spriteSourceSize": {
						"x": 0,
						"y": 0,
						"w": 29,
						"h": 30
					},
					"frame": {
						"x": 1150,
						"y": 63,
						"w": 29,
						"h": 30
					}
				},
				{
					"filename": "splitted/buttons/RPG_GUI_v1_selection-0028",
					"rotated": false,
					"trimmed": false,
					"sourceSize": {
						"w": 29,
						"h": 30
					},
					"spriteSourceSize": {
						"x": 0,
						"y": 0,
						"w": 29,
						"h": 30
					},
					"frame": {
						"x": 1181,
						"y": 63,
						"w": 29,
						"h": 30
					}
				},
				{
					"filename": "splitted/buttons/RPG_GUI_v1_selection-0035",
					"rotated": false,
					"trimmed": false,
					"sourceSize": {
						"w": 29,
						"h": 30
					},
					"spriteSourceSize": {
						"x": 0,
						"y": 0,
						"w": 29,
						"h": 30
					},
					"frame": {
						"x": 1212,
						"y": 64,
						"w": 29,
						"h": 30
					}
				},
				{
					"filename": "splitted/buttons/RPG_GUI_v1_selection-0038",
					"rotated": false,
					"trimmed": false,
					"sourceSize": {
						"w": 29,
						"h": 30
					},
					"spriteSourceSize": {
						"x": 0,
						"y": 0,
						"w": 29,
						"h": 30
					},
					"frame": {
						"x": 1243,
						"y": 64,
						"w": 29,
						"h": 30
					}
				},
				{
					"filename": "splitted/buttons/RPG_GUI_v1_selection-0049",
					"rotated": false,
					"trimmed": false,
					"sourceSize": {
						"w": 29,
						"h": 30
					},
					"spriteSourceSize": {
						"x": 0,
						"y": 0,
						"w": 29,
						"h": 30
					},
					"frame": {
						"x": 1274,
						"y": 64,
						"w": 29,
						"h": 30
					}
				},
				{
					"filename": "splitted/buttons/RPG_GUI_v1_selection-0052",
					"rotated": false,
					"trimmed": false,
					"sourceSize": {
						"w": 29,
						"h": 30
					},
					"spriteSourceSize": {
						"x": 0,
						"y": 0,
						"w": 29,
						"h": 30
					},
					"frame": {
						"x": 1305,
						"y": 64,
						"w": 29,
						"h": 30
					}
				},
				{
					"filename": "splitted/borders/RPG_GUI_v1_selection-0103",
					"rotated": false,
					"trimmed": false,
					"sourceSize": {
						"w": 19,
						"h": 32
					},
					"spriteSourceSize": {
						"x": 0,
						"y": 0,
						"w": 19,
						"h": 32
					},
					"frame": {
						"x": 1336,
						"y": 64,
						"w": 19,
						"h": 32
					}
				},
				{
					"filename": "splitted/borders/RPG_GUI_v1_selection-0105",
					"rotated": false,
					"trimmed": false,
					"sourceSize": {
						"w": 19,
						"h": 32
					},
					"spriteSourceSize": {
						"x": 0,
						"y": 0,
						"w": 19,
						"h": 32
					},
					"frame": {
						"x": 920,
						"y": 79,
						"w": 19,
						"h": 32
					}
				},
				{
					"filename": "splitted/buttons/RPG_GUI_v1_selection-0077",
					"rotated": false,
					"trimmed": false,
					"sourceSize": {
						"w": 29,
						"h": 30
					},
					"spriteSourceSize": {
						"x": 0,
						"y": 0,
						"w": 29,
						"h": 30
					},
					"frame": {
						"x": 941,
						"y": 76,
						"w": 29,
						"h": 30
					}
				},
				{
					"filename": "splitted/buttons/subtract",
					"rotated": false,
					"trimmed": false,
					"sourceSize": {
						"w": 29,
						"h": 30
					},
					"spriteSourceSize": {
						"x": 0,
						"y": 0,
						"w": 29,
						"h": 30
					},
					"frame": {
						"x": 972,
						"y": 76,
						"w": 29,
						"h": 30
					}
				},
				{
					"filename": "splitted/checkboxes/RPG_GUI_v1_selection-0023",
					"rotated": false,
					"trimmed": false,
					"sourceSize": {
						"w": 29,
						"h": 26
					},
					"spriteSourceSize": {
						"x": 0,
						"y": 0,
						"w": 29,
						"h": 26
					},
					"frame": {
						"x": 1003,
						"y": 76,
						"w": 29,
						"h": 26
					}
				},
				{
					"filename": "splitted/borders/single/RPG_GUI_v1_selection-0091",
					"rotated": false,
					"trimmed": false,
					"sourceSize": {
						"w": 26,
						"h": 26
					},
					"spriteSourceSize": {
						"x": 0,
						"y": 0,
						"w": 26,
						"h": 26
					},
					"frame": {
						"x": 1034,
						"y": 76,
						"w": 26,
						"h": 26
					}
				},
				{
					"filename": "splitted/borders/double/RPG_GUI_v1_selection-0061",
					"rotated": false,
					"trimmed": false,
					"sourceSize": {
						"w": 23,
						"h": 31
					},
					"spriteSourceSize": {
						"x": 0,
						"y": 0,
						"w": 23,
						"h": 31
					},
					"frame": {
						"x": 1062,
						"y": 69,
						"w": 23,
						"h": 31
					}
				},
				{
					"filename": "splitted/checkboxes/RPG_GUI_v1_selection-0007",
					"rotated": false,
					"trimmed": false,
					"sourceSize": {
						"w": 26,
						"h": 25
					},
					"spriteSourceSize": {
						"x": 0,
						"y": 0,
						"w": 26,
						"h": 25
					},
					"frame": {
						"x": 1062,
						"y": 102,
						"w": 26,
						"h": 25
					}
				},
				{
					"filename": "splitted/borders/double/RPG_GUI_v1_selection-0073",
					"rotated": false,
					"trimmed": false,
					"sourceSize": {
						"w": 23,
						"h": 31
					},
					"spriteSourceSize": {
						"x": 0,
						"y": 0,
						"w": 23,
						"h": 31
					},
					"frame": {
						"x": 1090,
						"y": 96,
						"w": 23,
						"h": 31
					}
				},
				{
					"filename": "splitted/checkboxes/RPG_GUI_v1_selection-0024",
					"rotated": false,
					"trimmed": false,
					"sourceSize": {
						"w": 29,
						"h": 26
					},
					"spriteSourceSize": {
						"x": 0,
						"y": 0,
						"w": 29,
						"h": 26
					},
					"frame": {
						"x": 1115,
						"y": 95,
						"w": 29,
						"h": 26
					}
				},
				{
					"filename": "splitted/borders/double/RPG_GUI_v1_selection-0071",
					"rotated": false,
					"trimmed": false,
					"sourceSize": {
						"w": 24,
						"h": 24
					},
					"spriteSourceSize": {
						"x": 0,
						"y": 0,
						"w": 24,
						"h": 24
					},
					"frame": {
						"x": 1146,
						"y": 95,
						"w": 24,
						"h": 24
					}
				},
				{
					"filename": "splitted/borders/double/RPG_GUI_v1_selection-0072",
					"rotated": false,
					"trimmed": false,
					"sourceSize": {
						"w": 24,
						"h": 24
					},
					"spriteSourceSize": {
						"x": 0,
						"y": 0,
						"w": 24,
						"h": 24
					},
					"frame": {
						"x": 1172,
						"y": 95,
						"w": 24,
						"h": 24
					}
				},
				{
					"filename": "splitted/borders/single/RPG_GUI_v1_selection-0097",
					"rotated": false,
					"trimmed": false,
					"sourceSize": {
						"w": 19,
						"h": 19
					},
					"spriteSourceSize": {
						"x": 0,
						"y": 0,
						"w": 19,
						"h": 19
					},
					"frame": {
						"x": 941,
						"y": 108,
						"w": 19,
						"h": 19
					}
				},
				{
					"filename": "splitted/borders/single/RPG_GUI_v1_selection-0084",
					"rotated": false,
					"trimmed": false,
					"sourceSize": {
						"w": 26,
						"h": 18
					},
					"spriteSourceSize": {
						"x": 0,
						"y": 0,
						"w": 26,
						"h": 18
					},
					"frame": {
						"x": 962,
						"y": 108,
						"w": 26,
						"h": 18
					}
				},
				{
					"filename": "splitted/radio-buttons/RPG_GUI_v1_selection-0002",
					"rotated": false,
					"trimmed": false,
					"sourceSize": {
						"w": 24,
						"h": 24
					},
					"spriteSourceSize": {
						"x": 0,
						"y": 0,
						"w": 24,
						"h": 24
					},
					"frame": {
						"x": 1198,
						"y": 96,
						"w": 24,
						"h": 24
					}
				},
				{
					"filename": "splitted/radio-buttons/RPG_GUI_v1_selection-0003",
					"rotated": false,
					"trimmed": false,
					"sourceSize": {
						"w": 24,
						"h": 24
					},
					"spriteSourceSize": {
						"x": 0,
						"y": 0,
						"w": 24,
						"h": 24
					},
					"frame": {
						"x": 1224,
						"y": 96,
						"w": 24,
						"h": 24
					}
				},
				{
					"filename": "splitted/radio-buttons/RPG_GUI_v1_selection-0004",
					"rotated": false,
					"trimmed": false,
					"sourceSize": {
						"w": 24,
						"h": 24
					},
					"spriteSourceSize": {
						"x": 0,
						"y": 0,
						"w": 24,
						"h": 24
					},
					"frame": {
						"x": 1250,
						"y": 96,
						"w": 24,
						"h": 24
					}
				},
				{
					"filename": "splitted/radio-buttons/RPG_GUI_v1_selection-0019",
					"rotated": false,
					"trimmed": false,
					"sourceSize": {
						"w": 24,
						"h": 24
					},
					"spriteSourceSize": {
						"x": 0,
						"y": 0,
						"w": 24,
						"h": 24
					},
					"frame": {
						"x": 1276,
						"y": 96,
						"w": 24,
						"h": 24
					}
				},
				{
					"filename": "splitted/radio-buttons/RPG_GUI_v1_selection-0020",
					"rotated": false,
					"trimmed": false,
					"sourceSize": {
						"w": 24,
						"h": 24
					},
					"spriteSourceSize": {
						"x": 0,
						"y": 0,
						"w": 24,
						"h": 24
					},
					"frame": {
						"x": 1302,
						"y": 96,
						"w": 24,
						"h": 24
					}
				},
				{
					"filename": "splitted/radio-buttons/RPG_GUI_v1_selection-0021",
					"rotated": false,
					"trimmed": false,
					"sourceSize": {
						"w": 24,
						"h": 24
					},
					"spriteSourceSize": {
						"x": 0,
						"y": 0,
						"w": 24,
						"h": 24
					},
					"frame": {
						"x": 1328,
						"y": 98,
						"w": 24,
						"h": 24
					}
				},
				{
					"filename": "splitted/borders/single/RPG_GUI_v1_selection-0093",
					"rotated": false,
					"trimmed": false,
					"sourceSize": {
						"w": 26,
						"h": 18
					},
					"spriteSourceSize": {
						"x": 0,
						"y": 0,
						"w": 26,
						"h": 18
					},
					"frame": {
						"x": 990,
						"y": 108,
						"w": 26,
						"h": 18
					}
				},
				{
					"filename": "splitted/borders/double/RPG_GUI_v1_selection-0044",
					"rotated": false,
					"trimmed": false,
					"sourceSize": {
						"w": 14,
						"h": 15
					},
					"spriteSourceSize": {
						"x": 0,
						"y": 0,
						"w": 14,
						"h": 15
					},
					"frame": {
						"x": 1018,
						"y": 104,
						"w": 14,
						"h": 15
					}
				},
				{
					"filename": "splitted/borders/double/RPG_GUI_v1_selection-0045",
					"rotated": false,
					"trimmed": false,
					"sourceSize": {
						"w": 14,
						"h": 15
					},
					"spriteSourceSize": {
						"x": 0,
						"y": 0,
						"w": 14,
						"h": 15
					},
					"frame": {
						"x": 1034,
						"y": 104,
						"w": 14,
						"h": 15
					}
				},
				{
					"filename": "splitted/borders/single/RPG_GUI_v1_selection-0080",
					"rotated": false,
					"trimmed": false,
					"sourceSize": {
						"w": 10,
						"h": 13
					},
					"spriteSourceSize": {
						"x": 0,
						"y": 0,
						"w": 10,
						"h": 13
					},
					"frame": {
						"x": 1050,
						"y": 104,
						"w": 10,
						"h": 13
					}
				},
				{
					"filename": "splitted/borders/single/RPG_GUI_v1_selection-0081",
					"rotated": false,
					"trimmed": false,
					"sourceSize": {
						"w": 11,
						"h": 13
					},
					"spriteSourceSize": {
						"x": 0,
						"y": 0,
						"w": 11,
						"h": 13
					},
					"frame": {
						"x": 905,
						"y": 104,
						"w": 11,
						"h": 13
					}
				}
			]
		}
	],
	"meta": {
		"app": "https://www.codeandweb.com/texturepacker",
		"version": "3.0",
		"smartupdate": "$TexturePacker:SmartUpdate:91ee7bec389792aab56ee4ede7483710:c43331f1d5fd1750ea9c1d8aef9c7a2d:b92f23b4669879880ae365ee307679f0$"
	}
}
